SearchPilot/__init__.py
SearchPilot/_base_client.py
SearchPilot/_client.py
SearchPilot/_compat.py
SearchPilot/_constants.py
SearchPilot/_exceptions.py
SearchPilot/_files.py
SearchPilot/_models.py
SearchPilot/_qs.py
SearchPilot/_resource.py
SearchPilot/_response.py
SearchPilot/_streaming.py
SearchPilot/_types.py
SearchPilot/_version.py
SearchPilot/pagination.py
SearchPilot/py.typed
SearchPilot/_utils/__init__.py
SearchPilot/_utils/_compat.py
SearchPilot/_utils/_datetime_parse.py
SearchPilot/_utils/_logs.py
SearchPilot/_utils/_proxy.py
SearchPilot/_utils/_reflection.py
SearchPilot/_utils/_resources_proxy.py
SearchPilot/_utils/_streams.py
SearchPilot/_utils/_sync.py
SearchPilot/_utils/_transform.py
SearchPilot/_utils/_typing.py
SearchPilot/_utils/_utils.py
SearchPilot/lib/.keep
SearchPilot/resources/__init__.py
SearchPilot/resources/accounts.py
SearchPilot/resources/customers.py
SearchPilot/resources/experiments.py
SearchPilot/resources/rules.py
SearchPilot/resources/sections.py
SearchPilot/resources/seo_experiment_results.py
SearchPilot/resources/steps.py
SearchPilot/resources/values.py
SearchPilot/types/__init__.py
SearchPilot/types/account_list_params.py
SearchPilot/types/customer_list_params.py
SearchPilot/types/experiment_list_params.py
SearchPilot/types/rule_list_params.py
SearchPilot/types/section_list_params.py
SearchPilot/types/seo_experiment_result_list_params.py
SearchPilot/types/step_list_params.py
SearchPilot/types/value_list_params.py
SearchPilot/types/shared/__init__.py
SearchPilot/types/shared/account.py
SearchPilot/types/shared/customer.py
SearchPilot/types/shared/experiment.py
SearchPilot/types/shared/rule.py
SearchPilot/types/shared/section.py
SearchPilot/types/shared/seo_experiment_result.py
SearchPilot/types/shared/step.py
SearchPilot/types/shared/value.py
searchpilot-0.6.0.dist-info/METADATA
searchpilot-0.6.0.dist-info/WHEEL
searchpilot-0.6.0.dist-info/licenses/LICENSE
searchpilot-0.6.0.dist-info/RECORD
